setup.py
scripts/run_an_election
turnout_election_schemes/__init__.py
turnout_election_schemes.egg-info/PKG-INFO
turnout_election_schemes.egg-info/SOURCES.txt
turnout_election_schemes.egg-info/dependency_links.txt
turnout_election_schemes.egg-info/top_level.txt
turnout_election_schemes/schemes/__init__.py
turnout_election_schemes/schemes/election_results.py
turnout_election_schemes/schemes/errors.py
turnout_election_schemes/schemes/scheme_runner.py
turnout_election_schemes/schemes/majorityjudgement/__init__.py
turnout_election_schemes/schemes/majorityjudgement/algorithm.py
turnout_election_schemes/schemes/majorityjudgement/count.py
turnout_election_schemes/schemes/majorityjudgement/runner.py
turnout_election_schemes/schemes/majorityjudgement/scheme.py
turnout_election_schemes/schemes/majorityjudgement/vote_aggregator.py
turnout_election_schemes/schemes/singletransferablevote/__init__.py
turnout_election_schemes/schemes/singletransferablevote/candidate.py
turnout_election_schemes/schemes/singletransferablevote/scheme.py
turnout_election_schemes/schemes/singletransferablevote/stv_round.py
turnout_election_schemes/schemes/singletransferablevote/vote.py