Metadata-Version: 1.1
Name: turnout-election-schemes
Version: 0.3
Summary: Library implementing (some) modern election schemes.
Home-page: https://github.com/devfort/turnout-election-schemes
Author: /dev/fort 9
Author-email: turnout-elections@groups.google.com
License: MIT
Platform: UNKNOWN
Classifier: Intended Audience :: Developers
Classifier: License :: OSI Approved :: MIT License
Classifier: Programming Language :: Python :: 2
